oarepo_s3_cli/__init__.py
oarepo_s3_cli/clickdef.py
oarepo_s3_cli/constants.py
oarepo_s3_cli/lib.py
oarepo_s3_cli/parallels.py
oarepo_s3_cli/utils.py
oarepo_s3_cli/version.py
oarepo_s3_cli-0.1.11.dist-info/AUTHORS.rst
oarepo_s3_cli-0.1.11.dist-info/LICENSE
oarepo_s3_cli-0.1.11.dist-info/METADATA
oarepo_s3_cli-0.1.11.dist-info/WHEEL
oarepo_s3_cli-0.1.11.dist-info/entry_points.txt
oarepo_s3_cli-0.1.11.dist-info/top_level.txt
oarepo_s3_cli-0.1.11.dist-info/RECORD
